ghga_datasteward_kit/__init__.py
ghga_datasteward_kit/__main__.py
ghga_datasteward_kit/batch_s3_upload.py
ghga_datasteward_kit/catalog_accession_generator.py
ghga_datasteward_kit/config.py
ghga_datasteward_kit/file_deletion.py
ghga_datasteward_kit/file_ingest.py
ghga_datasteward_kit/loading.py
ghga_datasteward_kit/main.py
ghga_datasteward_kit/metadata.py
ghga_datasteward_kit/models.py
ghga_datasteward_kit/utils.py
ghga_datasteward_kit/cli/__init__.py
ghga_datasteward_kit/cli/file.py
ghga_datasteward_kit/cli/main.py
ghga_datasteward_kit/cli/metadata.py
ghga_datasteward_kit/s3_upload/__init__.py
ghga_datasteward_kit/s3_upload/config.py
ghga_datasteward_kit/s3_upload/entrypoint.py
ghga_datasteward_kit/s3_upload/exceptions.py
ghga_datasteward_kit/s3_upload/file_decryption.py
ghga_datasteward_kit/s3_upload/file_encryption.py
ghga_datasteward_kit/s3_upload/http_client.py
ghga_datasteward_kit/s3_upload/multipart_upload.py
ghga_datasteward_kit/s3_upload/uploader.py
ghga_datasteward_kit/s3_upload/utils.py
ghga_datasteward_kit-5.2.0.dist-info/licenses/LICENSE
ghga_datasteward_kit-5.2.0.dist-info/METADATA
ghga_datasteward_kit-5.2.0.dist-info/WHEEL
ghga_datasteward_kit-5.2.0.dist-info/entry_points.txt
ghga_datasteward_kit-5.2.0.dist-info/top_level.txt
ghga_datasteward_kit-5.2.0.dist-info/RECORD
