Metadata-Version: 2.4
Name: ghga_datasteward_kit
Version: 5.2.0
Summary: GHGA Data Steward Kit - A utils package for GHGA data stewards.
Author-email: "German Human Genome Phenome Archive (GHGA)" <contact@ghga.de>
License: Apache 2.0
Project-URL: Repository, https://github.com/ghga-de/ghga-datasteward-kit
Classifier: Development Status :: 5 - Production/Stable
Classifier: Operating System :: POSIX :: Linux
Classifier: Programming Language :: Python :: 3
Classifier: Programming Language :: Python :: 3.12
Classifier: License :: OSI Approved :: Apache Software License
Classifier: Topic :: Internet :: WWW/HTTP :: HTTP Servers
Classifier: Topic :: Software Development :: Libraries
Classifier: Intended Audience :: Developers
Requires-Python: ~=3.12
License-File: LICENSE
Requires-Dist: crypt4gh<2,>=1.6
Requires-Dist: hexkit[s3]>=5.3
Requires-Dist: ghga-transpiler<3,>=2.1.2
Requires-Dist: metldata<5,>=4.0.4
Requires-Dist: ghga-service-commons[transports]<7,>=6.0.0
Dynamic: license-file
